vestapol/__init__.py
vestapol/api/__init__.py
vestapol/api/api.py
vestapol/destinations/__init__.py
vestapol/destinations/base_destination.py
vestapol/destinations/gcp_destination.py
vestapol/destinations/local_destination.py
vestapol/external_tables.py
vestapol/py.typed
vestapol/web_resources/__init__.py
vestapol/web_resources/base_resource.py
vestapol/web_resources/csv_resource.py
vestapol/web_resources/github_resource.py
vestapol/web_resources/json_resource.py
vestapol/writers/__init__.py
vestapol/writers/json_writer.py
vestapol/writers/text_writer.py
vestapol-0.0.28.dist-info/METADATA
vestapol-0.0.28.dist-info/WHEEL
vestapol-0.0.28.dist-info/licenses/LICENSE
vestapol-0.0.28.dist-info/RECORD
