Metadata-Version: 2.4
Name: vestapol
Version: 0.0.28
Summary: Python package that loads data from the web and deploys a corresponding external table definition, so that the data can be queried using standard SQL.
License: Apache-2.0
License-File: LICENSE
Author: Brian Waligorski
Author-email: bwaligorski@inquirer.com
Requires-Python: >=3.12
Classifier: License :: OSI Approved :: Apache Software License
Classifier: Programming Language :: Python :: 3
Classifier: Programming Language :: Python :: 3.12
Classifier: Programming Language :: Python :: 3.13
Classifier: Programming Language :: Python :: 3.14
Requires-Dist: google-cloud-bigquery (>=2.31)
Requires-Dist: google-cloud-storage (>=1.43)
Requires-Dist: pendulum (>=3.1,<4.0)
Requires-Dist: requests (>=2.26,<3.0)
Project-URL: Homepage, https://github.com/phillymedia/vestapol
Project-URL: Repository, https://github.com/phillymedia/vestapol
